Exercise/4.8/4.8.sv
module mux8 (
    input logic [2:0] s,  // 3-bit select signal
    input logic d0, d1, d2, d3, d4, d5, d6, d7,  // 8 input data signals
    output logic y        // output
);

always_comb begin
    case (s)
        3'b000: y = d0;  // when s=000, output = d0
        3'b001: y = d1;  // when s=001, output = d1
        3'b010: y = d2;  // when s=010, output = d2
        3'b011: y = d3;  // when s=011, output = d3
        3'b100: y = d4;  // when s=100, output = d4
        3'b101: y = d5;  // when s=101, output = d5
        3'b110: y = d6;  // when s=110, output = d6
        3'b111: y = d7;  // when s=111, output = d7
        default: y = 1'b0;  // default case (should never happen)
    endcase
end

endmodule

Exercise/4.8/mux8_tb.sv
// Simple testbench for beginners
module mux8_tb_simple;
    // Test signals
    reg [2:0] s;
    reg d0, d1, d2, d3, d4, d5, d6, d7;
    wire y;
    
    // Instantiate mux8
    mux8 dut (
        .s(s),
        .d0(d0), .d1(d1), .d2(d2), .d3(d3),
        .d4(d4), .d5(d5), .d6(d6), .d7(d7),
        .y(y)
    );
    
    // Test sequence
    initial begin
        // Create waveform file
        $dumpfile("mux8_simple.vcd");
        $dumpvars(0, mux8_tb_simple);
        
        // Initialize display
        $display("Time\t Select\t Inputs (d0-d7)\t Output");
        $display("--------------------------------------------");
        
        // Test case 1: Basic test
        d0 = 0; d1 = 1; d2 = 0; d3 = 1;
        d4 = 0; d5 = 1; d6 = 0; d7 = 1;
        
        // Test all select values
        s = 3'b000; #10; $display("%0t\t 000\t 0 1 0 1 0 1 0 1\t %b", $time, y);
        s = 3'b001; #10; $display("%0t\t 001\t 0 1 0 1 0 1 0 1\t %b", $time, y);
        s = 3'b010; #10; $display("%0t\t 010\t 0 1 0 1 0 1 0 1\t %b", $time, y);
        s = 3'b011; #10; $display("%0t\t 011\t 0 1 0 1 0 1 0 1\t %b", $time, y);
        s = 3'b100; #10; $display("%0t\t 100\t 0 1 0 1 0 1 0 1\t %b", $time, y);
        s = 3'b101; #10; $display("%0t\t 101\t 0 1 0 1 0 1 0 1\t %b", $time, y);
        s = 3'b110; #10; $display("%0t\t 110\t 0 1 0 1 0 1 0 1\t %b", $time, y);
        s = 3'b111; #10; $display("%0t\t 111\t 0 1 0 1 0 1 0 1\t %b", $time, y);
        
        // Test case 2: All zeros
        $display("\nAll inputs = 0:");
        d0 = 0; d1 = 0; d2 = 0; d3 = 0;
        d4 = 0; d5 = 0; d6 = 0; d7 = 0;
        s = 3'b010; #10; $display("%0t\t 010\t 0 0 0 0 0 0 0 0\t %b", $time, y);
        
        // Test case 3: All ones
        $display("\nAll inputs = 1:");
        d0 = 1; d1 = 1; d2 = 1; d3 = 1;
        d4 = 1; d5 = 1; d6 = 1; d7 = 1;
        s = 3'b101; #10; $display("%0t\t 101\t 1 1 1 1 1 1 1 1\t %b", $time, y);
        
        $display("\nSimulation completed!");
        #10 $finish;
    end
endmodule

Exercise/4.8/project_1/project_1.sim/sim_1/behav/xsim/mux8_simple.vcd
$date
   Wed Dec 24 17:39:26 2025
$end
$version
  2019.2
$end
$timescale
  1ps
$end
$scope module mux8_tb_simple $end
$var reg 3 ! s [2:0] $end
$var reg 1 " d0 $end
$var reg 1 # d1 $end
$var reg 1 $ d2 $end
$var reg 1 % d3 $end
$var reg 1 & d4 $end
$var reg 1 ' d5 $end
$var reg 1 ( d6 $end
$var reg 1 ) d7 $end
$var wire 1 * y $end
$scope module dut $end
$var wire 3 + s [2:0] $end
$var wire 1 , d0 $end
$var wire 1 - d1 $end
$var wire 1 . d2 $end
$var wire 1 / d3 $end
$var wire 1 0 d4 $end
$var wire 1 1 d5 $end
$var wire 1 2 d6 $end
$var wire 1 3 d7 $end
$var reg 1 4 y $end
$upscope $end
$upscope $end
$enddefinitions $end
#0
$dumpvars
b0 !
0"
1#
0$
1%
0&
1'
0(
1)
0*
b0 +
0,
1-
0.
1/
00
11
02
13
04
$end
#10000
b1 !
1*
b1 +
14
#20000
b10 !
0*
b10 +
04
#30000
b11 !
1*
b11 +
14
#40000
b100 !
0*
b100 +
04
#50000
b101 !
1*
b101 +
14
#60000
b110 !
0*
b110 +
04
#70000
b111 !
1*
b111 +
14
#80000
b10 !
0#
0%
0'
0)
0*
b10 +
0-
0/
01
03
04
